euclidian/__init__.py
euclidian/cartesian.py
euclidian/cartesian2.py
euclidian/cartesian3.py
euclidian/clipping.py
euclidian/flipping.py
euclidian/graycode.py
euclidian/util.py
euclidian/version.py
euclidian-0.9.4.dist-info/LICENCE.txt
euclidian-0.9.4.dist-info/METADATA
euclidian-0.9.4.dist-info/WHEEL
euclidian-0.9.4.dist-info/top_level.txt
euclidian-0.9.4.dist-info/zip-safe
euclidian-0.9.4.dist-info/RECORD
